fastapiview/__init__.py
fastapiview/__version__.py
fastapiclassview-0.0.1.dist-info/LICENSE
fastapiclassview-0.0.1.dist-info/METADATA
fastapiclassview-0.0.1.dist-info/WHEEL
fastapiclassview-0.0.1.dist-info/top_level.txt
fastapiclassview-0.0.1.dist-info/RECORD
