Metadata-Version: 2.1
Name: fastapiclassview
Version: 0.0.1
Summary: FastAPIView Class View
Home-page: https://github.com/ShiLiangAPI/FastAPIView.git
Author: ShiLiang
Author-email: 2509144896@qq.com
License: GPL-3.0-or-later
Classifier: License :: OSI Approved :: GNU General Public License v3 or later (GPLv3+)
Classifier: Programming Language :: Python
Classifier: Programming Language :: Python :: 3
Classifier: Programming Language :: Python :: 3.6
Classifier: Programming Language :: Python :: Implementation :: CPython
Classifier: Programming Language :: Python :: Implementation :: PyPy
Requires-Python: >=3.6.0
License-File: LICENSE
